odoo/addons/sale_order_search_line/README.rst
odoo/addons/sale_order_search_line/__init__.py
odoo/addons/sale_order_search_line/__manifest__.py
odoo/addons/sale_order_search_line/i18n/it.po
odoo/addons/sale_order_search_line/i18n/sale_order_search_line.pot
odoo/addons/sale_order_search_line/readme/DESCRIPTION.rst
odoo/addons/sale_order_search_line/static/description/icon.png
odoo/addons/sale_order_search_line/static/description/index.html
odoo/addons/sale_order_search_line/views/sale_order_views.xml
odoo_addon_sale_order_search_line-16.0.1.0.0.4.dist-info/METADATA
odoo_addon_sale_order_search_line-16.0.1.0.0.4.dist-info/WHEEL
odoo_addon_sale_order_search_line-16.0.1.0.0.4.dist-info/top_level.txt
odoo_addon_sale_order_search_line-16.0.1.0.0.4.dist-info/RECORD
